{
  "id": "puzzle-003",
  "week": 3,
  "title": "Motorcycles — Week 3",
  "difficulty": "Easy",
  "category": "Motorcycles",
  "theme": "Motorcycles",
  "rows": 13,
  "cols": 13,
  "grid": [
    [
      null,
      null,
      null,
      null,
      null,
      "C",
      "L",
      "U",
      "T",
      "C",
      "H",
      null,
      null
    ],
    [
      null,
      null,
      null,
      null,
      null,
      null,
      null,
      null,
      "W",
      null,
      "O",
      null,
      null
    ],
    [
      null,
      null,
      null,
      "E",
      "N",
      "D",
      "U",
      "R",
      "O",
      null,
      "N",
      null,
      null
    ],
    [
      null,
      null,
      null,
      null,
      null,
      null,
      null,
      null,
      "S",
      null,
      "D",
      null,
      null
    ],
    [
      null,
      "S",
      "P",
      "R",
      "O",
      "C",
      "K",
      "E",
      "T",
      null,
      "A",
      null,
      null
    ],
    [
      null,
      null,
      null,
      null,
      null,
      "H",
      null,
      null,
      "R",
      null,
      null,
      null,
      null
    ],
    [
      null,
      "D",
      "E",
      "S",
      "M",
      "O",
      "D",
      "R",
      "O",
      "M",
      "I",
      "C",
      null
    ],
    [
      null,
      null,
      null,
      null,
      null,
      "P",
      null,
      null,
      "K",
      null,
      "N",
      null,
      "D"
    ],
    [
      "T",
      "R",
      "I",
      "U",
      "M",
      "P",
      "H",
      null,
      "E",
      null,
      "D",
      null,
      "U"
    ],
    [
      null,
      null,
      null,
      null,
      null,
      "E",
      null,
      null,
      null,
      null,
      "I",
      null,
      "C"
    ],
    [
      "B",
      "O",
      "B",
      "B",
      "E",
      "R",
      null,
      "Y",
      "A",
      "M",
      "A",
      "H",
      "A"
    ],
    [
      null,
      null,
      null,
      "M",
      null,
      null,
      null,
      null,
      null,
      null,
      "N",
      null,
      "T"
    ],
    [
      null,
      "K",
      "A",
      "W",
      "A",
      "S",
      "A",
      "K",
      "I",
      null,
      null,
      null,
      "I"
    ]
  ],
  "across": [
    {
      "number": 1,
      "answer": "CLUTCH",
      "clue": "Hand lever that disengages the engine from the gearbox",
      "startRow": 0,
      "startCol": 5,
      "direction": "across"
    },
    {
      "number": 4,
      "answer": "ENDURO",
      "clue": "Off-road motorcycle discipline over long distances",
      "startRow": 2,
      "startCol": 3,
      "direction": "across"
    },
    {
      "number": 5,
      "answer": "SPROCKET",
      "clue": "Toothed wheel that drives the motorcycle chain",
      "startRow": 4,
      "startCol": 1,
      "direction": "across"
    },
    {
      "number": 7,
      "answer": "DESMODROMIC",
      "clue": "Ducati valve system that mechanically closes valves",
      "startRow": 6,
      "startCol": 1,
      "direction": "across"
    },
    {
      "number": 10,
      "answer": "TRIUMPH",
      "clue": "British marque that built the Bonneville",
      "startRow": 8,
      "startCol": 0,
      "direction": "across"
    },
    {
      "number": 11,
      "answer": "BOBBER",
      "clue": "Stripped-down custom motorcycle style",
      "startRow": 10,
      "startCol": 0,
      "direction": "across"
    },
    {
      "number": 13,
      "answer": "YAMAHA",
      "clue": "Japanese marque known for the R1 superbike",
      "startRow": 10,
      "startCol": 7,
      "direction": "across"
    },
    {
      "number": 14,
      "answer": "KAWASAKI",
      "clue": "Japanese marque behind the Ninja series",
      "startRow": 12,
      "startCol": 1,
      "direction": "across"
    }
  ],
  "down": [
    {
      "number": 2,
      "answer": "TWOSTROKE",
      "clue": "Engine type that fires every revolution",
      "startRow": 0,
      "startCol": 8,
      "direction": "down"
    },
    {
      "number": 3,
      "answer": "HONDA",
      "clue": "Japanese marque behind the Gold Wing tourer",
      "startRow": 0,
      "startCol": 10,
      "direction": "down"
    },
    {
      "number": 6,
      "answer": "CHOPPER",
      "clue": "Custom motorcycle style with extended forks",
      "startRow": 4,
      "startCol": 5,
      "direction": "down"
    },
    {
      "number": 8,
      "answer": "INDIAN",
      "clue": "Historic American marque older than Harley-Davidson",
      "startRow": 6,
      "startCol": 10,
      "direction": "down"
    },
    {
      "number": 9,
      "answer": "DUCATI",
      "clue": "Italian marque famed for its desmodromic valves",
      "startRow": 7,
      "startCol": 12,
      "direction": "down"
    },
    {
      "number": 12,
      "answer": "BMW",
      "clue": "German marque known for the boxer-engine GS series",
      "startRow": 10,
      "startCol": 3,
      "direction": "down"
    }
  ],
  "author": "Autocrosswords Studio",
  "estimatedTime": 4
}
